zaptools/__init__.py
zaptools/adapters.py
zaptools/client.py
zaptools/connection_router.py
zaptools/connectors.py
zaptools/protocols.py
zaptools/py.typed
zaptools/zap_logger.py
zaptools/core/__init__.py
zaptools/core/event_processor.py
zaptools/core/events.py
zaptools/core/id_controller.py
zaptools/core/websocket_connection.py
zaptools-0.5.2.dist-info/licenses/LICENSE
zaptools-0.5.2.dist-info/METADATA
zaptools-0.5.2.dist-info/WHEEL
zaptools-0.5.2.dist-info/top_level.txt
zaptools-0.5.2.dist-info/RECORD
