Metadata-Version: 2.4
Name: zaptools
Version: 0.5.2
Summary: A toolkit for Event-Driven websocket management
Author-email: Nathan Mejia <nathandraco22@gmail.com>
License: The MIT License (MIT)
Project-URL: Homepage, https://github.com/NathanDraco22/zaptools-python
Project-URL: Changelog, https://github.com/NathanDraco22/zaptools-python/blob/main/CHANGELOG.md
Classifier: Development Status :: 4 - Beta
Classifier: Intended Audience :: Developers
Classifier: License :: OSI Approved :: MIT License
Classifier: Programming Language :: Python
Classifier: Programming Language :: Python :: 3.10
Requires-Python: >=3.10
License-File: LICENSE
Requires-Dist: rich>=13.9.4
Requires-Dist: websockets>=14.1
Provides-Extra: dev
Requires-Dist: fastapi[standard]>=0.115.12; extra == "dev"
Requires-Dist: pytest>=8.3.5; extra == "dev"
Dynamic: license-file
